orchester_cli.py
orchester/ConfigHelper.py
orchester/ConnectorManager.py
orchester/Exceptions.py
orchester/__init__.py
orchester/connectors/AbstractBaseConnector.py
orchester/connectors/GDriveConnector.py
orchester/connectors/GithubConnector.py
orchester/connectors/SlackConnector.py
orchester/connectors/TrelloConnector.py
orchester/connectors/__init__.py
orchester/utils/__init__.py
orchester/utils/gen_gdrive_token.py
orchester/utils/gen_slack_token.py
orchester/utils/gen_trello_token.py
orchester-0.0.4.dist-info/LICENSE
orchester-0.0.4.dist-info/METADATA
orchester-0.0.4.dist-info/WHEEL
orchester-0.0.4.dist-info/entry_points.txt
orchester-0.0.4.dist-info/top_level.txt
orchester-0.0.4.dist-info/RECORD
