Metadata-Version: 2.1
Name: orchester
Version: 0.0.4
Summary: Orchester allows you to easily add/remove use to your favorite platforms.
Home-page: https://github.com/popojargo/orchester
Author: Alexis Côté
Author-email: alexiscote19@hotmail.com
License: MIT
Keywords: orchester auth trello github drive google groups slack manage cli
Platform: UNKNOWN
Classifier: Intended Audience :: Developers
Classifier: License :: OSI Approved :: MIT License
Classifier: Natural Language :: English
Classifier: Programming Language :: Python :: 3
Classifier: Programming Language :: Python :: 3.5
Classifier: Programming Language :: Python :: 3.6
Requires-Python: ~=3.5
Requires-Dist: Flask (<2,>=1.0.2)
Requires-Dist: google-api-python-client (<2,>=1.7.7)
Requires-Dist: oauth2client (<5,>=4.1.3)
Requires-Dist: py-trello (<1,>=0.14.0)
Requires-Dist: PyGithub (<2,>=1.43.4)
Requires-Dist: slackclient (<2,>=1.3.0)
